{"version":1,"resource":"vscode-remote://freecodecam-boilerplate-dqdnvzl46td.ws-us116.gitpod.io/workspace/boilerplate-advancednode/server.js","entries":[{"id":"Rfgp.js","timestamp":1728421003933},{"id":"yn4r.js","timestamp":1728421030845},{"id":"22C3.js","timestamp":1728421044353},{"id":"sfpa.js","timestamp":1728421083909},{"id":"PtHj.js","timestamp":1728421103185},{"id":"38jh.js","timestamp":1728421117421},{"id":"hOlE.js","timestamp":1728421143493},{"id":"tw7o.js","timestamp":1728421157565},{"id":"ryyT.js","timestamp":1728421187905},{"id":"PXVK.js","timestamp":1728421203197},{"id":"cufl.js","timestamp":1728421229985},{"id":"TSpX.js","timestamp":1728421261525},{"id":"sbjo.js","timestamp":1728421286609},{"id":"rRyt.js","timestamp":1728421304697},{"id":"fknk.js","timestamp":1728421330389},{"id":"UhkA.js","timestamp":1728421352741},{"id":"0gs9.js","timestamp":1728421379217},{"id":"oyVK.js","timestamp":1728421398909},{"id":"DAas.js","timestamp":1728421551317},{"id":"ClEX.js","timestamp":1728421570153},{"id":"zlpt.js","timestamp":1728421597445},{"id":"mtPH.js","timestamp":1728422804760},{"id":"Wn2j.js","timestamp":1728422824496},{"id":"bAAq.js","timestamp":1728422839020},{"id":"Kouh.js","timestamp":1728422881352},{"id":"cC6e.js","timestamp":1728422918952},{"id":"Q8Cn.js","timestamp":1728422933312},{"id":"IyEd.js","timestamp":1728423036204},{"id":"w38t.js","source":"undoRedo.source","timestamp":1728423050804},{"id":"0BkX.js","timestamp":1728423169907},{"id":"FXSY.js","timestamp":1728423198047},{"id":"x5OA.js","timestamp":1728423221527},{"id":"Yxen.js","timestamp":1728423312831},{"id":"l3Co.js","source":"undoRedo.source","timestamp":1728423338039},{"id":"jlj7.js","timestamp":1728423366079},{"id":"MmYs.js","timestamp":1728423380667},{"id":"qKGz.js","timestamp":1728423449683},{"id":"79Ob.js","timestamp":1728424941042},{"id":"Q8YS.js","timestamp":1728425260042},{"id":"E8JO.js","timestamp":1728425286938},{"id":"niut.js","timestamp":1728425316746},{"id":"238o.js","timestamp":1728425409669},{"id":"WuCR.js","timestamp":1728425498297},{"id":"Tgdt.js","timestamp":1728425550081},{"id":"tzI9.js","timestamp":1728425595901},{"id":"cvUx.js","timestamp":1728425793181},{"id":"u6CX.js","timestamp":1728425836053},{"id":"tS7j.js","timestamp":1728425861637},{"id":"2TtN.js","timestamp":1728425923349},{"id":"30uw.js","timestamp":1728425999861}]}